{
	"todos": [
		{
			"title": "hello ",
			"description": "world",
			"like": false,
			"star": false,
			"date": "2023-08-01T11:38:11.692Z",
			"completed": false,
			"id": 1
		}
	],
	"signup": [
		{
			"token": 768,
			"enterTime": "2023-06-05T09:33:29.768Z",
			"datas": {
				"fullName": "ali asgahr",
				"email": "alidonyaee64@gmail.com",
				"password": "Ali772359",
				"confirmPassword": "Ali772359"
			},
			"products": {},
			"id": 1
		}
	],
	"login": [
		{
			"fullName": "ali asgahr",
			"token": 768,
			"enterTime": "2023-06-05T09:33:29.768Z",
			"email": "alidonyaee64@gmail.com",
			"password": "Ali772359",
			"products": {},
			"id": 1
		}
	],
	"products": [
		{
			"iranianFoods": [
				{
					"name": "کوفنه برنجی",
					"discription": "برنج سبزی کوفته لپه آرد نخودچی، گردو و زرشک و آلو پیاز",
					"price": 180000,
					"img": "/public/assets/images/food-images/iranian-food/kofte.png",
					"star": 5,
					"off": {
						"condition": true,
						"off": 35
					}
				},
				{
					"name": "کشک بادمجان",
					"discription": "بادمجان، کشک، نعناع خشک، مغز گردو، سیر، پیاز",
					"price": 95000,
					"img": "/public/images/food-images/iranian-food/kashke-bademjan.png",
					"star": 5,
					"off": {
						"condition": false,
						"off": 0
					}
				},
				{
					"name": "میرزا قاسمی",
					"discription": "بادمجان، گوجه فرنگی، تخم مرغ، سیر، رب گوجه فرنگی",
					"price": 165000,
					"img": "/public/images/food-images/iranian-food/mirza-gasemi.png",
					"star": 5,
					"off": {
						"condition": true,
						"off": 10
					}
				},
				{
					"name": "باقلاقاتوق",
					"discription": "پاچ باقلا، شوید خشک، کره، سیر، تخم مرغ",
					"price": 205000,
					"img": "/public/images/food-images/iranian-food/baglagatog.png",
					"star": 4,
					"off": {
						"condition": true,
						"off": 10
					}
				},
				{
					"name": "فلافل",
					"discription": "نخود، پیاز، تخم گشنیز، سیر، جعفری، سیب زمینی",
					"price": 80000,
					"img": "/public/images/food-images/iranian-food/falafel.png",
					"star": 3,
					"off": {
						"condition": false,
						"off": 0
					}
				},
				{
					"name": "کله جوش",
					"discription": "کشک، گردو، پیاز، نعناع خشک",
					"price": 210000,
					"img": "/public/images/food-images/iranian-food/kalejosh.png",
					"star": 4,
					"off": {
						"condition": true,
						"off": 5
					}
				},
				{
					"name": "بورانی بادمجان",
					"discription": "بادمجان قلمی، ماست چکیده، سیر، روغن زیتون، مغز گردو",
					"price": 170000,
					"img": "/public/images/food-images/iranian-food/borani-bademjan.png",
					"star": 5,
					"off": {
						"condition": true,
						"off": 22
					}
				},
				{
					"name": "بادمجان شکم‌پر",
					"discription": "بادمجان، پیاز، گوجه فرنگی، سبزی خشک",
					"price": 150000,
					"img": "/public/images/food-images/iranian-food/bademjan-shekam-por.png",
					"star": 4,
					"off": {
						"condition": true,
						"off": 18
					}
				},
				{
					"name": "دلمه برگ کلم",
					"discription": "کلم برگ، برنج، لپه پخته، پیاز، سبزی معطر",
					"price": 220000,
					"img": "/public/images/food-images/iranian-food/dolme-kalam.png",
					"star": 5,
					"off": {
						"condition": true,
						"off": 8
					}
				},
				{
					"name": "دلمه برگ مو",
					"discription": "پیاز، برنج، لپه، سبزی دلمه، سرکه",
					"price": 190000,
					"img": "/public/images/food-images/iranian-food/dolme.png",
					"star": 2,
					"off": {
						"condition": false,
						"off": 0
					}
				},
				{
					"name": "کوکو سبزی",
					"discription": "تخم مرغ، گردو، سیر، آرد، روغن مایع سبزی کوکویی",
					"price": 300000,
					"img": "/public/images/food-images/iranian-food/koko-sabzi.png",
					"star": 5,
					"off": {
						"condition": true,
						"off": 10
					}
				},
				{
					"name": "کوکو سیب‌زمینی و عدس",
					"discription": "عدس، سیب زمینی، پیاز متوسط، تخم مرغ، پودر سیر، آرد سوخاری",
					"price": 135000,
					"img": "/public/images/food-images/iranian-food/dolme.png",
					"star": 1,
					"off": {
						"condition": true,
						"off": 20
					}
				}
			],
			"nonIraninaFoods": [
				{
					"name": "پاستا سبزیجات",
					"discription": "پاستا، قارچ، گوجه، کدوی خوردشده، پیاز خلالی‌شده",
					"price": 175000,
					"img": "/public/images/food-images/non-iranian-food/pasta-vejetable.png",
					"star": 5,
					"off": {
						"condition": true,
						"off": 20
					}
				},
				{
					"name": "پاستا بلونز",
					"discription": "اسپاگتی، گوشت چرخ کرده، هویج، ساقه کرفس، گوجه فرنگی، سیر، پیاز، پنیر پارمزان، روغن زیتون",
					"price": 170000,
					"img": "/public/images/food-images/non-iranian-food/pasta-blonze.png",
					"star": 4,
					"off": {
						"condition": true,
						"off": 12
					}
				},
				{
					"name": "راتاتویی",
					"discription": "بادمجان، گوجه فرنگی، کدو سبز، پیاز، رب گوجه فرنگی، روغن زیتون، پنیر پارمزان",
					"price": 180000,
					"img": "/public/images/food-images/non-iranian-food/ratatoi.png",
					"star": 4,
					"off": {
						"condition": true,
						"off": 45
					}
				},
				{
					"name": "سوشی",
					"discription": "جلبک دریایی/ نوری، برنج کته، سرکه سفید (یا سرکه برنج)، شکر، نمک دریا",
					"price": 100000,
					"img": "/public/images/food-images/non-iranian-food/soshi.png",
					"star": 4,
					"off": {
						"condition": true,
						"off": 15
					}
				},
				{
					"name": "پالاک پنیر ",
					"discription": "پنیر، اسفناج، گوجه، پیاز، سیر ",
					"price": 200000,
					"img": "/public/images/food-images/non-iranian-food/palag-panir.png",
					"star": 4,
					"off": {
						"condition": true,
						"off": 15
					}
				},
				{
					"name": "کالزونه اسفناج ",
					"discription": "اسفناج، قارچ، پنیر موزارلا یا پنیر پیتزا، پنیر ریکوتا یا پنیر خامه ای، پیاز، سیر، روغن زیتون ",
					"price": 190000,
					"img": "/public/images/food-images/non-iranian-food/kalzone.png",
					"star": 5,
					"off": {
						"condition": true,
						"off": 17
					}
				}
			],
			"pizzas": [
				{
					"name": "پیتزا روکولا",
					"discription": "اسفناج، سبزی روکولا، آرد، پودر مایه خمیر، روغن زیتون، خردل، سیر، پنیر موزارلا و پارمسان، گوجه گیلاسی ،سس فلفل سبز تند ",
					"price": 195000,
					"img": "/public/images/food-images/pizza/rokola.png",
					"star": 5,
					"off": {
						"condition": true,
						"off": 12
					}
				},
				{
					"name": "پیتزا بادمجان و زیتون",
					"discription": "بادمجان کوچک، روغن زیتون، پنیر موزارلا، پنیر پارمزان، برگ ریحان، گوجه فرنگی، سس گوجه فرنگی",
					"price": 150000,
					"img": "/public/images/food-images/pizza/bademjan-ziton.png",
					"star": 4,
					"off": {
						"condition": false,
						"off": 0
					}
				},
				{
					"name": "پیتزا سبزیجات و خامه",
					"discription": "نخود فرنگی پخته شده، ذرت نیم پز، فلفل دلمه‌ای رنگی، قارچ، سیر یا پیازچه خردشده",
					"price": 210000,
					"img": "/public/images/food-images/pizza/sabzichat-khame.png",
					"star": 4,
					"off": {
						"condition": true,
						"off": 21
					}
				},
				{
					"name": "پیتزا قارچ",
					"discription": "قارچ، فلفل دلمه ای، رب گوجه فرنگی، پودر سیر، آویشن، مرزه، پنیر پیتزا گیاهی",
					"price": 215000,
					"img": "/public/images/food-images/pizza/sabzichat-khame.png",
					"star": 3,
					"off": {
						"condition": true,
						"off": 25
					}
				},
				{
					"name": "پیتزا پپرونی",
					"discription": "تافو، فلفل قرمز خشک شده، پودر دانه‌های خردل، دانه رازیانه، پاپریکا دودی، پودر سیر، شکر نارگیل، پودر بادیان رومی ",
					"price": 100000,
					"img": "/public/images/food-images/pizza/peperoni.png",
					"star": 4,
					"off": {
						"condition": false,
						"off": 0
					}
				},
				{
					"name": "پیتزا اسفناج",
					"discription": "اسفناج تازه، پیاز، سیر، پنیر پیتزا، قارچ",
					"price": 280000,
					"img": "/public/images/food-images/pizza/esfenaj.png",
					"star": 5,
					"off": {
						"condition": true,
						"off": 10
					}
				},
				{
					"name": "پیتزا مارگاریتا",
					"discription": "گوجه فرنگی، ریحان، سیر، پنیر پیتزا",
					"price": 165000,
					"img": "/public/images/food-images/pizza/margarita.png",
					"star": 2,
					"off": {
						"condition": true,
						"off": 13
					}
				},
				{
					"name": "پیتزا پنیر",
					"discription": "نان پیتزا، پنیر پیتزا، سس باربیکیو، گوجه فرنگی، سس کچاپ، سیر، روغن زیتون",
					"price": 115000,
					"img": "/public/images/food-images/pizza/panir.png",
					"star": 3,
					"off": {
						"condition": true,
						"off": 16
					}
				}
			],
			"sandwitch": [
				{
					"name": "ساندویچ کتلت مخصوص",
					"discription": "سیب زمینی، لوبیا قرمز،  بلغور گندم، نعناع خشک، پودر زیره، پودر جوز هندی، گوجه فرنگی، روغن زیتون",
					"price": 230000,
					"img": "/public/images/food-images/sandwich/kotlet-makhsos.png",
					"star": 5,
					"off": {
						"condition": true,
						"off": 18
					}
				},
				{
					"name": "ساندویچ سوسیس کوکتل",
					"discription": "سوسیس گیاهی، پیاز، سیب زمینی،  رب گوجه فرنگی",
					"price": 205000,
					"img": "/public/images/food-images/sandwich/sosis-esfenaj.png",
					"star": 4,
					"off": {
						"condition": true,
						"off": 35
					}
				},
				{
					"name": "ساندویچ کتلت کدو سبز",
					"discription": "کدو سبز، هویج، سیب زمینی، پیاز",
					"price": 145000,
					"img": "/public/images/food-images/sandwich/kotlet-kadosabz.png",
					"star": 5,
					"off": {
						"condition": false,
						"off": 0
					}
				},
				{
					"name": "پنینی اسفناج",
					"discription": " قارچ، اسفناج، پیاز، پنیر پیتزا، خامه، پودر پاپریکا، گردو، سرکه بالزامیک، سس مایونز",
					"price": 210000,
					"img": "/public/images/food-images/sandwich/esfenaj.png",
					"star": 3,
					"off": {
						"condition": true,
						"off": 15
					}
				}
			]
		}
	],
	"product_shoes": [
		{
			"nike": [
				{
					"id": 1,
					"name": "model x",
					"brand": "NIKE",
					"price": 159.59,
					"off": 10,
					"imgurl": "../../assets/products/nike/1.png",
					"sizes": {
						"sm": 2,
						"md": 3,
						"lg": 0,
						"xl": 5,
						"2xl": 2
					},
					"color_1": "#000000",
					"color_2": "#ffc400"
				},
				{
					"id": 2,
					"name": "model y",
					"brand": "NIKE",
					"price": 179.35,
					"off": 0,
					"imgurl": "../../assets/products/nike/2.png",
					"sizes": {
						"sm": 0,
						"md": 32,
						"lg": 0,
						"xl": 55,
						"2xl": 20
					},
					"color_1": "#000000",
					"color_2": "#ff0000"
				},
				{
					"id": 3,
					"name": "model z",
					"brand": "NIKE",
					"price": 199.99,
					"off": 5,
					"imgurl": "../../assets/products/nike/3.png",
					"sizes": {
						"sm": 11,
						"md": 32,
						"lg": 15,
						"xl": 55,
						"2xl": 0
					},
					"color_1": "#00accf",
					"color_2": "#000000"
				},
				{
					"id": 4,
					"name": "model airmax",
					"brand": "NIKE",
					"price": 179.35,
					"off": 0,
					"imgurl": "../../assets/products/nike/4.png",
					"sizes": {
						"sm": 0,
						"md": 32,
						"lg": 0,
						"xl": 0,
						"2xl": 20
					},
					"color_1": "#ff3010",
					"color_2": "#525252"
				},
				{
					"id": 5,
					"name": "model airmax red",
					"brand": "NIKE",
					"price": 250.35,
					"off": 0,
					"imgurl": "../../assets/products/nike/5.png",
					"sizes": {
						"sm": 0,
						"md": 32,
						"lg": 15,
						"xl": 0,
						"2xl": 20
					},
					"color_1": "#e72121",
					"color_2": "#252525"
				},
				{
					"id": 5,
					"name": "model jordan",
					"brand": "NIKE",
					"price": 450.35,
					"off": 0,
					"imgurl": "../../assets/products/nike/6.png",
					"sizes": {
						"sm": 0,
						"md": 0,
						"lg": 15,
						"xl": 0,
						"2xl": 0
					},
					"color_1": "#d63535",
					"color_2": "#25b992"
				}
			],
			"adidas": [
				{
					"id": 1,
					"name": "model x",
					"brand": "ADIDAS",
					"price": 159.59,
					"off": 10,
					"imgurl": "../../assets/products/adidas/1.png",
					"sizes": {
						"sm": 2,
						"md": 3,
						"lg": 0,
						"xl": 5,
						"2xl": 2
					},
					"color_1": "#000000",
					"color_2": "#ffc400"
				},
				{
					"id": 2,
					"name": "model y",
					"brand": "ADIDAS",
					"price": 179.35,
					"off": 0,
					"imgurl": "../../assets/products/adidas/2.png",
					"sizes": {
						"sm": 0,
						"md": 32,
						"lg": 0,
						"xl": 55,
						"2xl": 20
					},
					"color_1": "#000000",
					"color_2": "#ff0000"
				},
				{
					"id": 3,
					"name": "model z",
					"brand": "ADIDAS",
					"price": 199.99,
					"off": 5,
					"imgurl": "../../assets/products/adidas/3.png",
					"sizes": {
						"sm": 11,
						"md": 32,
						"lg": 15,
						"xl": 55,
						"2xl": 0
					},
					"color_1": "#00accf",
					"color_2": "#000000"
				},
				{
					"id": 4,
					"name": "model airmax",
					"brand": "ADIDAS",
					"price": 179.35,
					"off": 0,
					"imgurl": "../../assets/products/adidas/4.png",
					"sizes": {
						"sm": 0,
						"md": 32,
						"lg": 0,
						"xl": 0,
						"2xl": 20
					},
					"color_1": "#ff3010",
					"color_2": "#525252"
				},
				{
					"id": 5,
					"name": "model airmax red",
					"brand": "ADIDAS",
					"price": 250.35,
					"off": 0,
					"imgurl": "../../assets/products/adidas/5.png",
					"sizes": {
						"sm": 0,
						"md": 32,
						"lg": 15,
						"xl": 0,
						"2xl": 20
					},
					"color_1": "#e72121",
					"color_2": "#252525"
				},
				{
					"id": 5,
					"name": "model jordan",
					"brand": "ADIDAS",
					"price": 450.35,
					"off": 0,
					"imgurl": "../../assets/products/adidas/6.png",
					"sizes": {
						"sm": 0,
						"md": 0,
						"lg": 15,
						"xl": 0,
						"2xl": 0
					},
					"color_1": "#d63535",
					"color_2": "#25b992"
				}
			],
			"new_balance": [
				{
					"id": 1,
					"name": "model x",
					"brand": "NEW BALANCE",
					"price": 159.59,
					"off": 10,
					"imgurl": "../../assets/products/nb/1.png",
					"sizes": {
						"sm": 2,
						"md": 3,
						"lg": 0,
						"xl": 5,
						"2xl": 2
					},
					"color_1": "#000000",
					"color_2": "#ffc400"
				},
				{
					"id": 2,
					"name": "model y",
					"brand": "NEW BALANCE",
					"price": 179.35,
					"off": 0,
					"imgurl": "../../assets/products/nb/2.png",
					"sizes": {
						"sm": 0,
						"md": 32,
						"lg": 0,
						"xl": 55,
						"2xl": 20
					},
					"color_1": "#000000",
					"color_2": "#ff0000"
				},
				{
					"id": 3,
					"name": "model z",
					"brand": "NEW BALANCE",
					"price": 199.99,
					"off": 5,
					"imgurl": "../../assets/products/nb/3.png",
					"sizes": {
						"sm": 11,
						"md": 32,
						"lg": 15,
						"xl": 55,
						"2xl": 0
					},
					"color_1": "#00accf",
					"color_2": "#000000"
				},
				{
					"id": 4,
					"name": "model airmax",
					"brand": "NEW BALANCE",
					"price": 179.35,
					"off": 0,
					"imgurl": "../../assets/products/nb/4.png",
					"sizes": {
						"sm": 0,
						"md": 32,
						"lg": 0,
						"xl": 0,
						"2xl": 20
					},
					"color_1": "#ff3010",
					"color_2": "#525252"
				},
				{
					"id": 5,
					"name": "model airmax red",
					"brand": "NEW BALANCE",
					"price": 250.35,
					"off": 0,
					"imgurl": "../../assets/products/nb/5.png",
					"sizes": {
						"sm": 0,
						"md": 32,
						"lg": 15,
						"xl": 0,
						"2xl": 20
					},
					"color_1": "#e72121",
					"color_2": "#252525"
				},
				{
					"id": 5,
					"name": "model jordan",
					"brand": "NEW BALANCE",
					"price": 450.35,
					"off": 0,
					"imgurl": "../../assets/products/nb/6.png",
					"sizes": {
						"sm": 0,
						"md": 0,
						"lg": 15,
						"xl": 0,
						"2xl": 0
					},
					"color_1": "#d63535",
					"color_2": "#25b992"
				}
			]
		}
	]
}
